flyer_composer/__init__.py
flyer_composer/__main__.py
flyer_composer/cli.py
flyer_composer/i18n.py
flyer_composer/gui/__init__.py
flyer_composer/gui/__main__.py
flyer_composer/gui/_backend_mupdf.py
flyer_composer/gui/_backend_poppler.py
flyer_composer/gui/application-exit.png
flyer_composer/gui/document-open.png
flyer_composer/gui/document-save-as.png
flyer_composer/gui/entry-delete.png
flyer_composer/gui/help-donate.png
flyer_composer/gui/pdf_backend.py
flyer_composer/locale/flyer-composer.pot
flyer_composer/locale/de/LC_MESSAGES/flyer-composer.mo
flyer_composer/locale/de/LC_MESSAGES/flyer-composer.po
flyer_composer/locale/es/LC_MESSAGES/flyer-composer.mo
flyer_composer/locale/es/LC_MESSAGES/flyer-composer.po
flyer_composer/locale/fr/LC_MESSAGES/flyer-composer.mo
flyer_composer/locale/fr/LC_MESSAGES/flyer-composer.po
flyer_composer/locale/nl/LC_MESSAGES/flyer-composer.mo
flyer_composer/locale/nl/LC_MESSAGES/flyer-composer.po
flyer_composer/locale/sv/LC_MESSAGES/flyer-composer.mo
flyer_composer/locale/sv/LC_MESSAGES/flyer-composer.po
flyer_composer-1.0.dist-info/licenses/LICENSES/AGPL-3.0-or-later.txt
flyer_composer-1.0.dist-info/licenses/LICENSES/CC0-1.0.txt
flyer_composer-1.0.dist-info/licenses/LICENSES/GFDL-1.3-or-later.txt
flyer_composer-1.0.dist-info/licenses/LICENSES/GPL-3.0-or-later.txt
flyer_composer-1.0.dist-info/METADATA
flyer_composer-1.0.dist-info/WHEEL
flyer_composer-1.0.dist-info/entry_points.txt
flyer_composer-1.0.dist-info/top_level.txt
flyer_composer-1.0.dist-info/RECORD
