Metadata-Version: 2.4
Name: flyer-composer
Version: 1.0
Summary: Rearrange PDF pages to print as flyers on one paper
Home-page: http://crazy-compilers.com/flyer-composer
Download-URL: https://pypi.org/project/flyer-composer/
Author: Hartmut Goebel
Author-email: h.goebel@crazy-compilers.com
License: AGPL-3.0-or-later
Keywords: pdf,flyer,leaflet
Classifier: Development Status :: 4 - Beta
Classifier: Environment :: Console
Classifier: Environment :: X11 Applications :: Qt
Classifier: Intended Audience :: Developers
Classifier: Intended Audience :: End Users/Desktop
Classifier: Intended Audience :: System Administrators
Classifier: Natural Language :: English
Classifier: Natural Language :: German
Classifier: Operating System :: OS Independent
Classifier: Programming Language :: Python
Classifier: Programming Language :: Python :: 3
Classifier: Programming Language :: Python :: 3.8
Classifier: Programming Language :: Python :: 3.9
Classifier: Programming Language :: Python :: 3.10
Classifier: Programming Language :: Python :: 3.11
Classifier: Programming Language :: Python :: 3.12
Classifier: Programming Language :: Python :: 3.13
Classifier: Topic :: Printing
Classifier: Topic :: Utilities
Requires-Python: >=3.8
License-File: LICENSES/AGPL-3.0-or-later.txt
License-File: LICENSES/CC0-1.0.txt
License-File: LICENSES/GFDL-1.3-or-later.txt
License-File: LICENSES/GPL-3.0-or-later.txt
Requires-Dist: pypdf>=5.5
Provides-Extra: gui
Requires-Dist: pyqt5; extra == "gui"
Requires-Dist: python-poppler-qt5; extra == "gui"
Dynamic: download-url
Dynamic: license-file
